# 字符串常量池StringTable

​		HotSpot VM里，记字符串字面值的一个全局表叫做 StringTable，它本质上就是个`HashTable `，其结构是一个数组，数组中每个元素是一个链表。JVM 内部的 HashTable 是不可以动态扩容的，即数组长度（位桶数量）是固定的

​		可以通过调整常量池位桶的数量对其进行调优，`-XX:StringTableSize=n`，n是一个正整数，最小的取值是 1009



## StringTable加载说明

```java
public class JavapString {

    public static void main(String[] args) {
        String a = "a";
        String b = "b";
        String ab = "ab";
        String abAdd = a + b;
    }

}
```



编译上面的 Java 文件之后，可以使用 `javap -v JavaString.class` 查看其信息

```java
Classfile /E:/workSpace/JavaTest/MiFrist/out/production/MiFrist/cn/dai/jvm/JavapString.class
  Last modified 2020-8-8; size 679 bytes
  MD5 checksum c4ce47f430e74c704af8d571bac4f155
  Compiled from "JavapString.java"
public class cn.dai.jvm.JavapString
  minor version: 0
  major version: 52
  flags: ACC_PUBLIC, ACC_SUPER
Constant pool:
   #1 = Methodref          #10.#29        // java/lang/Object."<init>":()V
   #2 = String             #22            // a
   #3 = String             #24            // b
   #4 = String             #25            // ab
   #5 = Class              #30            // java/lang/StringBuilder
   #6 = Methodref          #5.#29         // java/lang/StringBuilder."<init>":()V
   #7 = Methodref          #5.#31         // java/lang/StringBuilder.append:(Ljava/lang/String;)Ljava/lang/StringBuilder;
   #8 = Methodref          #5.#32         // java/lang/StringBuilder.toString:()Ljava/lang/String;
   #9 = Class              #33            // cn/dai/jvm/JavapString
  #10 = Class              #34            // java/lang/Object
  #11 = Utf8               <init>
  #12 = Utf8               ()V
  #13 = Utf8               Code
  #14 = Utf8               LineNumberTable
  #15 = Utf8               LocalVariableTable
  #16 = Utf8               this
  #17 = Utf8               Lcn/dai/jvm/JavapString;
  #18 = Utf8               main
  #19 = Utf8               ([Ljava/lang/String;)V
  #20 = Utf8               args
  #21 = Utf8               [Ljava/lang/String;
  #22 = Utf8               a
  #23 = Utf8               Ljava/lang/String;
  #24 = Utf8               b
  #25 = Utf8               ab
  #26 = Utf8               abAdd
  #27 = Utf8               SourceFile
  #28 = Utf8               JavapString.java
  #29 = NameAndType        #11:#12        // "<init>":()V
  #30 = Utf8               java/lang/StringBuilder
  #31 = NameAndType        #35:#36        // append:(Ljava/lang/String;)Ljava/lang/StringBuilder;
  #32 = NameAndType        #37:#38        // toString:()Ljava/lang/String;
  #33 = Utf8               cn/dai/jvm/JavapString
  #34 = Utf8               java/lang/Object
  #35 = Utf8               append
  #36 = Utf8               (Ljava/lang/String;)Ljava/lang/StringBuilder;
  #37 = Utf8               toString
  #38 = Utf8               ()Ljava/lang/String;
{
  public cn.dai.jvm.JavapString();
    descriptor: ()V
    flags: ACC_PUBLIC
    Code:
      stack=1, locals=1, args_size=1
         0: aload_0
         1: invokespecial #1                  // Method java/lang/Object."<init>":()V
         4: return
      LineNumberTable:
        line 11: 0
      LocalVariableTable:
        Start  Length  Slot  Name   Signature
            0       5     0  this   Lcn/dai/jvm/JavapString;

  public static void main(java.lang.String[]);
    descriptor: ([Ljava/lang/String;)V
    flags: ACC_PUBLIC, ACC_STATIC
    Code:
      stack=2, locals=5, args_size=1
         0: ldc           #2                  // String a
         2: astore_1
         3: ldc           #3                  // String b
         5: astore_2
         6: ldc           #4                  // String ab
         8: astore_3
         9: new           #5                  // class java/lang/StringBuilder
        12: dup
        13: invokespecial #6                  // Method java/lang/StringBuilder."<init>":()V
        16: aload_1
                  
        //这里说明调用StringBuilder.append("a");
        17: invokevirtual #7                  // Method java/lang/StringBuilder.append:(Ljava/lang/String;)Ljava/lang/StringBuilder;
        20: aload_2
                  
        //这里说明调用StringBuilder.append("b");
        21: invokevirtual #7                  // Method java/lang/StringBuilder.append:(Ljava/lang/String;)Ljava/lang/StringBuilder;
                  
        //这里说明 abAdd = StringBuilder.toString:();
        //toString 方法是创建一个新的String对象返回          
        24: invokevirtual #8                  // Method java/lang/StringBuilder.toString:()Ljava/lang/String;
        27: astore        4
        29: return
      LineNumberTable:
        line 14: 0
        line 15: 3
        line 16: 6
        line 17: 9
        line 18: 29
      LocalVariableTable://局部变量表;  Slot是插槽的意思
        Start  Length  Slot  Name   Signature
            0      30     0  args   [Ljava/lang/String;
            3      27     1     a   Ljava/lang/String;
            6      24     2     b   Ljava/lang/String;
            9      21     3    ab   Ljava/lang/String;
           29       1     4 abAdd   Ljava/lang/String;
}
SourceFile: "JavapString.java"
```



- 常量池的信息都会被加载到运行时常量池中，但是一开始 a,b,ab 字符串只是常量池中的符号
- 当使用到 a,b,ab 字符串时，就会将符号变为 java 字符串对象，然后放入到 StringTable 中（此时的 StringTable 指的是运行时的常量池）（懒加载特性）
- 但是 abAdd 对象是 new 产生的，该对象在堆中创建的，不会在运行时常量池中查找字符串，也不会将字符串放入到运行时常量池中

